dprint_utils/__init__.py
dprint_utils/utils.py
bear_dprint_utils-0.1.0.dist-info/METADATA
bear_dprint_utils-0.1.0.dist-info/WHEEL
bear_dprint_utils-0.1.0.dist-info/top_level.txt
bear_dprint_utils-0.1.0.dist-info/RECORD
