Metadata-Version: 2.4
Name: bear-dprint-utils
Version: 0.1.0
Summary: A utility to override the global print function with a timestamped version.
Author-email: Bohdan Riabunets <bearablyk@gmail.com>
License-Expression: MIT
Project-URL: Homepage, https://github.com/bearablyk/dprint-utils
Project-URL: Issues, https://github.com/bearablyk/dprint-utils/issues
Keywords: print,logging,timestamp,monkey-patching,utility
Classifier: Programming Language :: Python :: 3
Classifier: Operating System :: OS Independent
Classifier: Topic :: System :: Logging
Classifier: Topic :: Utilities
Requires-Python: >=3.8
